[
  {
    "name": "Reginald Frank Thornton",
    "username": "RFT07",
    "phone": "+27820658330",
    "played": 19,
    "wins": 15,
    "draws": 1,
    "losses": 3,
    "points": 46,
    "gf": 50,
    "ga": 15,
    "form": [
      "L",
      "W",
      "W",
      "W",
      "D",
      "W",
      "W",
      "W",
      "W",
      "W"
    ],
    "postponements": 17,
    "suspended": false
  },
  {
    "name": "Moosa",
    "username": "CRANK_",
    "phone": "+27699906125",
    "played": 20,
    "wins": 17,
    "draws": 1,
    "losses": 2,
    "points": 52,
    "gf": 51,
    "ga": 9,
    "form": [
      "W",
      "W",
      "W",
      "W",
      "W",
      "W",
      "L",
      "W",
      "W",
      "W"
    ],
    "postponements": 17,
    "suspended": false
  },
  {
    "name": "Sailor",
    "username": "Sailor",
    "phone": "+27677514331",
    "played": 19,
    "wins": 3,
    "draws": 6,
    "losses": 10,
    "points": 15,
    "gf": 9,
    "ga": 30,
    "form": [
      "W",
      "L",
      "L",
      "D",
      "D",
      "W",
      "D",
      "L",
      "D",
      "D"
    ],
    "postponements": 18,
    "suspended": false
  },
  {
    "name": "👑•",
    "username": "Zan-Ten",
    "phone": "+27710050307",
    "played": 19,
    "wins": 8,
    "draws": 1,
    "losses": 10,
    "points": 25,
    "gf": 22,
    "ga": 26,
    "form": [
      "L",
      "W",
      "L",
      "L",
      "W",
      "W",
      "L",
      "L",
      "D",
      "L"
    ],
    "postponements": 20,
    "suspended": false
  },
  {
    "name": "El Tigre",
    "username": "Nigelmj21",
    "phone": "+27656657141",
    "played": 19,
    "wins": 15,
    "draws": 1,
    "losses": 3,
    "points": 46,
    "gf": 42,
    "ga": 12,
    "form": [
      "W",
      "W",
      "W",
      "W",
      "W",
      "W",
      "W",
      "W",
      "D",
      "W"
    ],
    "postponements": 12,
    "suspended": false
  },
  {
    "name": "mansur",
    "username": "ICONIC-CLUB",
    "phone": "+255616502631",
    "played": 20,
    "wins": 8,
    "draws": 6,
    "losses": 6,
    "points": 30,
    "gf": 29,
    "ga": 18,
    "form": [
      "L",
      "W",
      "D",
      "L",
      "W",
      "D",
      "L",
      "W",
      "D",
      "L"
    ],
    "postponements": 19,
    "suspended": false
  },
  {
    "name": "DJ Ronaldo ZA",
    "username": "djronaldoza",
    "phone": "+27711764627",
    "played": 14,
    "wins": 2,
    "draws": 3,
    "losses": 9,
    "points": 9,
    "gf": 6,
    "ga": 25,
    "form": [
      "W",
      "W",
      "L",
      "D",
      "L",
      "L",
      "D",
      "L",
      "L",
      "L"
    ],
    "postponements": 16,
    "suspended": true
  },
  {
    "name": "Lucky7",
    "username": "CodeTalker",
    "phone": "+27684880622",
    "played": 21,
    "wins": 4,
    "draws": 8,
    "losses": 9,
    "points": 20,
    "gf": 10,
    "ga": 28,
    "form": [
      "W",
      "L",
      "D",
      "D",
      "L",
      "D",
      "L",
      "L",
      "L",
      "D"
    ],
    "postponements": 19,
    "suspended": false
  },
  {
    "name": "Thandobhaze",
    "username": "Bhaze",
    "phone": "+27679687240",
    "played": 23,
    "wins": 2,
    "draws": 9,
    "losses": 12,
    "points": 15,
    "gf": 4,
    "ga": 34,
    "form": [
      "D",
      "W",
      "L",
      "L",
      "L",
      "D",
      "D",
      "L",
      "L",
      "D"
    ],
    "postponements": 20,
    "suspended": false
  },
  {
    "name": "🅿️🅾️🕉️🅱️🅰️",
    "username": "RoyalAM",
    "phone": "+27682987402",
    "played": 21,
    "wins": 3,
    "draws": 7,
    "losses": 11,
    "points": 16,
    "gf": 11,
    "ga": 33,
    "form": [
      "L",
      "D",
      "L",
      "L",
      "L",
      "L",
      "D",
      "D",
      "D",
      "L"
    ],
    "postponements": 18,
    "suspended": false
  },
  {
    "name": "Ctaum",
    "username": "Ctaum-cpt",
    "phone": "+27764797158",
    "played": 23,
    "wins": 15,
    "draws": 1,
    "losses": 7,
    "points": 46,
    "gf": 55,
    "ga": 16,
    "form": [
      "W",
      "L",
      "W",
      "W",
      "W",
      "W",
      "D",
      "W",
      "W",
      "L"
    ],
    "postponements": 20,
    "suspended": false
  },
  {
    "name": "Zlatan",
    "username": "Gillie11",
    "phone": "+270660513301",
    "played": 6,
    "wins": 4,
    "draws": 2,
    "losses": 0,
    "points": 14,
    "gf": 11,
    "ga": 5,
    "form": [
      "W",
      "W",
      "W",
      "D",
      "W",
      "D"
    ],
    "postponements": 0,
    "suspended": true
  },
  {
    "name": "Sibusiso Makhanye❤️😎🇿🇦",
    "username": "YungboyShlime",
    "phone": "+27810878650",
    "played": 21,
    "wins": 1,
    "draws": 9,
    "losses": 11,
    "points": 12,
    "gf": 7,
    "ga": 31,
    "form": [
      "L",
      "D",
      "L",
      "D",
      "D",
      "L",
      "D",
      "D",
      "L",
      "D"
    ],
    "postponements": 20,
    "suspended": false
  },
  {
    "name": "Dilibo👑",
    "username": "DiliboL",
    "phone": "+27760348136",
    "played": 20,
    "wins": 10,
    "draws": 5,
    "losses": 5,
    "points": 35,
    "gf": 27,
    "ga": 16,
    "form": [
      "L",
      "W",
      "W",
      "W",
      "W",
      "D",
      "L",
      "D",
      "D",
      "L"
    ],
    "postponements": 15,
    "suspended": false
  },
  {
    "name": "Mk Liyas",
    "username": "Nyali11",
    "phone": "+27786218748",
    "played": 19,
    "wins": 7,
    "draws": 3,
    "losses": 9,
    "points": 24,
    "gf": 24,
    "ga": 19,
    "form": [
      "W",
      "L",
      "L",
      "L",
      "W",
      "W",
      "L",
      "D",
      "L",
      "W"
    ],
    "postponements": 19,
    "suspended": false
  },
  {
    "name": "DJ THABISO KOMAKO",
    "username": "Kloutt",
    "phone": "+27792135785",
    "played": 20,
    "wins": 1,
    "draws": 5,
    "losses": 14,
    "points": 8,
    "gf": 1,
    "ga": 58,
    "form": [
      "L",
      "L",
      "L",
      "L",
      "L",
      "D",
      "L",
      "L",
      "W",
      "D"
    ],
    "postponements": 16,
    "suspended": false
  },
  {
    "name": "SMANGALISO",
    "username": "SMANGALISO",
    "phone": "+27780070989",
    "played": 19,
    "wins": 8,
    "draws": 5,
    "losses": 6,
    "points": 29,
    "gf": 23,
    "ga": 18,
    "form": [
      "W",
      "L",
      "W",
      "W",
      "L",
      "W",
      "D",
      "W",
      "D",
      "D"
    ],
    "postponements": 17,
    "suspended": false
  },
  {
    "name": "XWRLD 🕴🏼",
    "username": "XWRLD_REAPERS",
    "phone": "+27750656258",
    "played": 17,
    "wins": 9,
    "draws": 3,
    "losses": 5,
    "points": 30,
    "gf": 24,
    "ga": 13,
    "form": [
      "W",
      "W",
      "W",
      "D",
      "W",
      "W",
      "L",
      "L",
      "L",
      "D"
    ],
    "postponements": 7,
    "suspended": false
  }
]